bounce_desktop/__init__.py
bounce_desktop/_core.cpython-310-x86_64-linux-gnu.so
bounce_desktop/_core.cpython-311-x86_64-linux-gnu.so
bounce_desktop/_core.cpython-312-x86_64-linux-gnu.so
bounce_desktop/_vendored/weston/bin/di-edid-decode
bounce_desktop/_vendored/weston/bin/edid-decode
bounce_desktop/_vendored/weston/bin/wcap-decode
bounce_desktop/_vendored/weston/bin/weston
bounce_desktop/_vendored/weston/bin/weston-calibrator
bounce_desktop/_vendored/weston/bin/weston-debug
bounce_desktop/_vendored/weston/bin/weston-screenshooter
bounce_desktop/_vendored/weston/bin/weston-simple-damage
bounce_desktop/_vendored/weston/bin/weston-simple-dmabuf-egl
bounce_desktop/_vendored/weston/bin/weston-simple-dmabuf-feedback
bounce_desktop/_vendored/weston/bin/weston-simple-dmabuf-v4l
bounce_desktop/_vendored/weston/bin/weston-simple-egl
bounce_desktop/_vendored/weston/bin/weston-simple-shm
bounce_desktop/_vendored/weston/bin/weston-simple-touch
bounce_desktop/_vendored/weston/bin/weston-terminal
bounce_desktop/_vendored/weston/bin/weston-touch-calibrator
bounce_desktop/_vendored/weston/etc/pam.d/weston-remote-access
bounce_desktop/_vendored/weston/include/aml.h
bounce_desktop/_vendored/weston/include/libdisplay-info/cta.h
bounce_desktop/_vendored/weston/include/libdisplay-info/cvt.h
bounce_desktop/_vendored/weston/include/libdisplay-info/displayid.h
bounce_desktop/_vendored/weston/include/libdisplay-info/dmt.h
bounce_desktop/_vendored/weston/include/libdisplay-info/edid.h
bounce_desktop/_vendored/weston/include/libdisplay-info/gtf.h
bounce_desktop/_vendored/weston/include/libdisplay-info/info.h
bounce_desktop/_vendored/weston/include/libweston-15/libweston/backend-headless.h
bounce_desktop/_vendored/weston/include/libweston-15/libweston/backend-vnc.h
bounce_desktop/_vendored/weston/include/libweston-15/libweston/colorimetry.h
bounce_desktop/_vendored/weston/include/libweston-15/libweston/config-parser.h
bounce_desktop/_vendored/weston/include/libweston-15/libweston/desktop.h
bounce_desktop/_vendored/weston/include/libweston-15/libweston/libweston.h
bounce_desktop/_vendored/weston/include/libweston-15/libweston/linalg-3.h
bounce_desktop/_vendored/weston/include/libweston-15/libweston/linalg-4.h
bounce_desktop/_vendored/weston/include/libweston-15/libweston/linalg-types.h
bounce_desktop/_vendored/weston/include/libweston-15/libweston/linalg.h
bounce_desktop/_vendored/weston/include/libweston-15/libweston/matrix.h
bounce_desktop-0.3.0.dist-info/METADATA
bounce_desktop-0.3.0.dist-info/WHEEL
bounce_desktop-0.3.0.dist-info/licenses/LICENSE
bounce_desktop-0.3.0.dist-info/RECORD
