Metadata-Version: 2.4
Name: bounce_desktop
Version: 0.3.0
Summary: Hardware-accelerated Linux virtual desktops.
License-Expression: MIT
License-File: LICENSE
Author: William Henning
Author-email: wchenningwchenning@gmail.com
Requires-Python: >=3.10
Classifier: Programming Language :: Python :: 3
Classifier: Programming Language :: Python :: 3.10
Classifier: Programming Language :: Python :: 3.11
Classifier: Programming Language :: Python :: 3.12
Classifier: Programming Language :: Python :: 3.13
Classifier: Programming Language :: Python :: 3.14
Requires-Dist: meson (>=1.10.0,<2.0.0)
Requires-Dist: numpy (>=2.2.0,<3.0.0)
Project-URL: Homepage, https://github.com/Whenning42/bounce-desktop
